odoo8_addon_l10n_es_account_invoice_sequence-8.0.1.3.0.99.dev15-py3.6-nspkg.pth
odoo_addons/l10n_es_account_invoice_sequence/README.rst
odoo_addons/l10n_es_account_invoice_sequence/__init__.py
odoo_addons/l10n_es_account_invoice_sequence/__openerp__.py
odoo_addons/l10n_es_account_invoice_sequence/constants.py
odoo_addons/l10n_es_account_invoice_sequence/hooks.py
odoo_addons/l10n_es_account_invoice_sequence/data/sequence_data.xml
odoo_addons/l10n_es_account_invoice_sequence/i18n/bg.po
odoo_addons/l10n_es_account_invoice_sequence/i18n/ca.po
odoo_addons/l10n_es_account_invoice_sequence/i18n/ca_ES.po
odoo_addons/l10n_es_account_invoice_sequence/i18n/cs.po
odoo_addons/l10n_es_account_invoice_sequence/i18n/en_US.po
odoo_addons/l10n_es_account_invoice_sequence/i18n/es.po
odoo_addons/l10n_es_account_invoice_sequence/i18n/es_CR.po
odoo_addons/l10n_es_account_invoice_sequence/i18n/fr.po
odoo_addons/l10n_es_account_invoice_sequence/i18n/gl.po
odoo_addons/l10n_es_account_invoice_sequence/i18n/hr.po
odoo_addons/l10n_es_account_invoice_sequence/i18n/l10n_es_account_invoice_sequence.pot
odoo_addons/l10n_es_account_invoice_sequence/i18n/nl.po
odoo_addons/l10n_es_account_invoice_sequence/i18n/pl.po
odoo_addons/l10n_es_account_invoice_sequence/i18n/pt.po
odoo_addons/l10n_es_account_invoice_sequence/i18n/pt_BR.po
odoo_addons/l10n_es_account_invoice_sequence/i18n/ru.po
odoo_addons/l10n_es_account_invoice_sequence/i18n/sl.po
odoo_addons/l10n_es_account_invoice_sequence/i18n/sv.po
odoo_addons/l10n_es_account_invoice_sequence/i18n/tr.po
odoo_addons/l10n_es_account_invoice_sequence/i18n/vi.po
odoo_addons/l10n_es_account_invoice_sequence/models/__init__.py
odoo_addons/l10n_es_account_invoice_sequence/models/account_invoice.py
odoo_addons/l10n_es_account_invoice_sequence/models/account_journal.py
odoo_addons/l10n_es_account_invoice_sequence/static/description/icon.png
odoo_addons/l10n_es_account_invoice_sequence/tests/__init__.py
odoo8_addon_l10n_es_account_invoice_sequence-8.0.1.3.0.99.dev15.dist-info/METADATA
odoo8_addon_l10n_es_account_invoice_sequence-8.0.1.3.0.99.dev15.dist-info/WHEEL
odoo8_addon_l10n_es_account_invoice_sequence-8.0.1.3.0.99.dev15.dist-info/namespace_packages.txt
odoo8_addon_l10n_es_account_invoice_sequence-8.0.1.3.0.99.dev15.dist-info/top_level.txt
odoo8_addon_l10n_es_account_invoice_sequence-8.0.1.3.0.99.dev15.dist-info/RECORD
